slixmpp-1.12.0.dist-info/METADATA
slixmpp-1.12.0.dist-info/WHEEL
slixmpp-1.12.0.dist-info/licenses/LICENSE
slixmpp.libs/libgcc_s-69c45f16.so.1
slixmpp/__init__.py
slixmpp/api.py
slixmpp/basexmpp.py
slixmpp/clientxmpp.py
slixmpp/componentxmpp.py
slixmpp/exceptions.py
slixmpp/features/__init__.py
slixmpp/features/feature_bind/__init__.py
slixmpp/features/feature_bind/bind.py
slixmpp/features/feature_bind/stanza.py
slixmpp/features/feature_mechanisms/__init__.py
slixmpp/features/feature_mechanisms/mechanisms.py
slixmpp/features/feature_mechanisms/stanza/__init__.py
slixmpp/features/feature_mechanisms/stanza/abort.py
slixmpp/features/feature_mechanisms/stanza/auth.py
slixmpp/features/feature_mechanisms/stanza/challenge.py
slixmpp/features/feature_mechanisms/stanza/failure.py
slixmpp/features/feature_mechanisms/stanza/mechanisms.py
slixmpp/features/feature_mechanisms/stanza/response.py
slixmpp/features/feature_mechanisms/stanza/success.py
slixmpp/features/feature_preapproval/__init__.py
slixmpp/features/feature_preapproval/preapproval.py
slixmpp/features/feature_preapproval/stanza.py
slixmpp/features/feature_rosterver/__init__.py
slixmpp/features/feature_rosterver/rosterver.py
slixmpp/features/feature_rosterver/stanza.py
slixmpp/features/feature_session/__init__.py
slixmpp/features/feature_session/session.py
slixmpp/features/feature_session/stanza.py
slixmpp/features/feature_starttls/__init__.py
slixmpp/features/feature_starttls/stanza.py
slixmpp/features/feature_starttls/starttls.py
slixmpp/jid.py
slixmpp/jid.rs
slixmpp/plugins/__init__.py
slixmpp/plugins/base.py
slixmpp/plugins/xep_0004/__init__.py
slixmpp/plugins/xep_0004/dataforms.py
slixmpp/plugins/xep_0004/stanza/__init__.py
slixmpp/plugins/xep_0004/stanza/field.py
slixmpp/plugins/xep_0004/stanza/form.py
slixmpp/plugins/xep_0009/__init__.py
slixmpp/plugins/xep_0009/binding.py
slixmpp/plugins/xep_0009/remote.py
slixmpp/plugins/xep_0009/rpc.py
slixmpp/plugins/xep_0009/stanza.py
slixmpp/plugins/xep_0012/__init__.py
slixmpp/plugins/xep_0012/last_activity.py
slixmpp/plugins/xep_0012/stanza.py
slixmpp-1.12.0.dist-info/RECORD
